tradata_core/__init__.py
tradata_core/config/__init__.py
tradata_core/config/settings.py
tradata_core/core/__init__.py
tradata_core/core/engine.py
tradata_core/core/formatter.py
tradata_core/core/handler.py
tradata_core/core/logger.py
tradata_core/middleware/__init__.py
tradata_core/middleware/fastapi.py
tradata_core/middleware/flask.py
tradata_core/utils/__init__.py
tradata_core/utils/cache_helper.py
tradata_core/utils/context.py
tradata_core/utils/decorators.py
tradata_core/utils/response_builder.py
tradata_core-0.2.6.dist-info/licenses/LICENSE
tradata_core-0.2.6.dist-info/METADATA
tradata_core-0.2.6.dist-info/WHEEL
tradata_core-0.2.6.dist-info/top_level.txt
tradata_core-0.2.6.dist-info/RECORD
