Metadata-Version: 2.4
Name: tradata-core
Version: 0.2.6
Summary: Professional core framework for trading applications
Author-email: Tradata Team <team@tradata.com>
License: MIT
Project-URL: Homepage, https://github.com/TradataTech/tradata-core-py
Project-URL: Repository, https://github.com/TradataTech/tradata-core-py
Project-URL: Documentation, https://github.com/TradataTech/tradata-core-py/tree/main/docs
Project-URL: Changelog, https://github.com/TradataTech/tradata-core-py/blob/main/CHANGELOG.md
Project-URL: Issues, https://github.com/TradataTech/tradata-core-py/issues
Project-URL: Discussions, https://github.com/TradataTech/tradata-core-py/discussions
Classifier: Development Status :: 4 - Beta
Classifier: Intended Audience :: Developers
Classifier: License :: OSI Approved :: MIT License
Classifier: Programming Language :: Python :: 3
Classifier: Programming Language :: Python :: 3.8
Classifier: Programming Language :: Python :: 3.9
Classifier: Programming Language :: Python :: 3.10
Classifier: Programming Language :: Python :: 3.11
Classifier: Topic :: System :: Monitoring
Classifier: Topic :: Software Development :: Libraries :: Python Modules
Classifier: Topic :: Internet :: WWW/HTTP :: HTTP Servers
Classifier: Topic :: Scientific/Engineering :: Information Analysis
Requires-Python: >=3.8
License-File: LICENSE
Requires-Dist: fastapi>=0.68.0
Requires-Dist: starlette>=0.14.0
Requires-Dist: pydantic>=1.8.0
Requires-Dist: python-json-logger>=2.0.0
Requires-Dist: httpx>=0.27.0
Provides-Extra: dev
Requires-Dist: pytest>=6.0; extra == "dev"
Requires-Dist: pytest-cov; extra == "dev"
Requires-Dist: pytest-benchmark; extra == "dev"
Requires-Dist: pytest-asyncio; extra == "dev"
Requires-Dist: black; extra == "dev"
Requires-Dist: flake8; extra == "dev"
Requires-Dist: mypy; extra == "dev"
Requires-Dist: build; extra == "dev"
Provides-Extra: test
Requires-Dist: pytest>=7.0.0; extra == "test"
Requires-Dist: pytest-cov>=4.0.0; extra == "test"
Requires-Dist: pytest-asyncio>=0.21.0; extra == "test"
Requires-Dist: httpx>=0.24.0; extra == "test"
Provides-Extra: docs
Requires-Dist: sphinx>=5.0.0; extra == "docs"
Requires-Dist: sphinx-rtd-theme>=1.0.0; extra == "docs"
Requires-Dist: myst-parser>=0.18.0; extra == "docs"
Dynamic: license-file
